<?xml version="1.0" encoding="utf-8" ?>
<Defs>

  <BodyPartDef>
    <defName>FrontLeftFlipper</defName>
    <label>front left flipper</label>
    <hitPoints>30</hitPoints>
    <permanentInjuryChanceFactor>0.08</permanentInjuryChanceFactor>
    <skinCovered>true</skinCovered>
    <tags>
      <li>MovingLimbCore</li>
    </tags>
  </BodyPartDef>

  <BodyPartDef>
    <defName>FrontRightFlipper</defName>
    <label>front right flipper</label>
    <hitPoints>30</hitPoints>
    <permanentInjuryChanceFactor>0.08</permanentInjuryChanceFactor>
    <skinCovered>true</skinCovered>
    <tags>
      <li>MovingLimbCore</li>
    </tags>
  </BodyPartDef>


</Defs>